<annotation>
	<folder>jpg</folder>
	<filename>398_cropped.jpg</filename>
	<path>../img/398_cropped.jpg</path>
	<source>
		<database>Unknown</database>
	</source>
	<size>
		<width>1024</width>
		<height>682</height>
		<depth>3</depth>
	</size>
	<segmented>0</segmented>
	<object>
		<name>plastic</name>
		<pose>Unspecified</pose>
		<truncated>0</truncated>
		<difficult>0</difficult>
		<bndbox>
			<xmin>450</xmin>
			<ymin>444</ymin>
			<xmax>579</xmax>
			<ymax>513</ymax>
		</bndbox>
	</object>
</annotation>
